RBFMeshGen/__init__.py
RBFMeshGen/geometry_utils.py
RBFMeshGen/mesh_generation.py
RBFMeshGen/visualization_tools.py
RBFMeshGen-1.0.5.dist-info/METADATA
RBFMeshGen-1.0.5.dist-info/WHEEL
RBFMeshGen-1.0.5.dist-info/top_level.txt
RBFMeshGen-1.0.5.dist-info/RECORD
