Metadata-Version: 2.1
Name: RBFMeshGen
Version: 1.0.5
Summary: A Python package for generating random meshes based on radial basis functions.
Home-page: https://github.com/LDBreton/RBFMeshGen
Author: Louis Breton
Author-email: louis.breton@ciencias.unam.mx
Classifier: Programming Language :: Python :: 3
Classifier: License :: OSI Approved :: MIT License
Classifier: Operating System :: OS Independent
Requires-Python: >=3.6
Requires-Dist: numpy
Requires-Dist: matplotlib
Requires-Dist: shapely
